pyBLUP/QC.py
pyBLUP/QK.py
pyBLUP/__init__.py
pyBLUP/cpu_inspect.py
pyBLUP/gwas.py
pyBLUP/kfold.py
pyBLUP/mlm.py
pyBLUP/pca.py
pyblup-1.0.5.dist-info/METADATA
pyblup-1.0.5.dist-info/WHEEL
pyblup-1.0.5.dist-info/licenses/LICENSE
pyblup-1.0.5.dist-info/RECORD
