Metadata-Version: 2.4
Name: pyBLUP
Version: 1.0.5
License-File: LICENSE
Requires-Python: <3.14,>=3.9
Requires-Dist: joblib>=1.5.2
Requires-Dist: numpy
Requires-Dist: psutil
Requires-Dist: scipy
